{
    "data": [
        {
            "itemType": "write",
            "item": {
                "itemName": "i am item name and i am goint to tuncate",
                "itemModule": "i am module1",
                "itemStem": "i am item stem and i am going to stem",
                "itemType": "write"
            },
            "categories": {},
            "difficulty": "Moderate1",
            "status": "Approved",
            "lastUpdated": {
                "time": "Sun Dec 1 1995 03:24:00 GMT+1000 (Australian Eastern Standard Time)",
                "person": "Fangyuan Xu"
            },
            "actions": {}
        },
        {
            "itemType": "write",
            "item": {
                "itemName": "i am item name and i am goint to tuncate",
                "itemModule": "i am module2",
                "itemStem": "i am item stem and i am going to stem",
                "itemType": "write"
            },
            "categories": {},
            "difficulty": "Moderate2",
            "status": "Approved",
            "lastUpdated": {
                "time": "Sun Dec 2 1995 03:24:00 GMT+1000 (Australian Eastern Standard Time)",
                "person": "Fangyuan Xu"
            },
            "actions": {}
        },
        {
            "itemType": "write",
            "item": {
                "itemName": "i am item name and i am goint to tuncate",
                "itemModule": "i am module3",
                "itemStem": "i am item stem and i am going to stem",
                "itemType": "write"
            },
            "categories": {},
            "difficulty": "Moderate3",
            "status": "Approved",
            "lastUpdated": {
                "time": "Sun Dec 3 1995 03:24:00 GMT+1000 (Australian Eastern Standard Time)",
                "person": "Fangyuan Xu"
            },
            "actions": {}
        },
        {
            "itemType": "write",
            "item": {
                "itemName": "i am item name and i am goint to tuncate",
                "itemModule": "i am module4",
                "itemStem": "i am item stem and i am going to stem",
                "itemType": "write"
            },
            "categories": {},
            "difficulty": "Moderate4",
            "status": "Approved",
            "lastUpdated": {
                "time": "Sun Dec 4 1995 03:24:00 GMT+1000 (Australian Eastern Standard Time)",
                "person": "Fangyuan Xu"
            },
            "actions": {}
        },
        {
            "itemType": "write",
            "item": {
                "itemName": "i am item name and i am goint to tuncate",
                "itemModule": "i am module5",
                "itemStem": "i am item stem and i am going to stem",
                "itemType": "write"
            },
            "categories": {},
            "difficulty": "Moderate5",
            "status": "Approved",
            "lastUpdated": {
                "time": "Sun Dec 5 1995 03:24:00 GMT+1000 (Australian Eastern Standard Time)",
                "person": "Fangyuan Xu"
            },
            "actions": {}
        },
        {
            "itemType": "write",
            "item": {
                "itemName": "i am item name and i am goint to tuncate",
                "itemModule": "i am module6",
                "itemStem": "i am item stem and i am going to stem",
                "itemType": "write"
            },
            "categories": {},
            "difficulty": "Moderate",
            "status": "Approved",
            "lastUpdated": {
                "time": "Sun Dec 6 1995 03:24:00 GMT+1000 (Australian Eastern Standard Time)",
                "person": "Fangyuan Xu"
            },
            "actions": {}
        },
        {
            "itemType": "write",
            "item": {
                "itemName": "i am item name and i am goint to tuncate",
                "itemModule": "i am module7",
                "itemStem": "i am item stem and i am going to stem",
                "itemType": "write"
            },
            "categories": {},
            "difficulty": "Moderate6",
            "status": "Approved",
            "lastUpdated": {
                "time": "Sun Dec 7 1995 03:24:00 GMT+1000 (Australian Eastern Standard Time)",
                "person": "Fangyuan Xu"
            },
            "actions": {}
        },
        {
            "itemType": "write",
            "item": {
                "itemName": "i am item name and i am goint to tuncate",
                "itemModule": "i am module8",
                "itemStem": "i am item stem and i am going to stem",
                "itemType": "write"
            },
            "categories": {},
            "difficulty": "Moderate7",
            "status": "Approved",
            "lastUpdated": {
                "time": "Sun Dec 17 1996 03:24:00 GMT+1000 (Australian Eastern Standard Time)",
                "person": "Fangyuan Xu"
            },
            "actions": {}
        },
        {
            "itemType": "write",
            "item": {
                "itemName": "i am item name and i am goint to tuncate",
                "itemModule": "i am module9",
                "itemStem": "i am item stem and i am going to stem",
                "itemType": "write"
            },
            "categories": {},
            "difficulty": "Moderate8",
            "status": "Approved",
            "lastUpdated": {
                "time": "Sun Dec 17 1996 03:24:00 GMT+1000 (Australian Eastern Standard Time)",
                "person": "Fangyuan Xu"
            },
            "actions": {}
        },
        {
            "itemType": "write",
            "item": {
                "itemName": "i am item name and i am goint to tuncate",
                "itemModule": "i am module10",
                "itemStem": "i am item stem and i am going to stem",
                "itemType": "write"
            },
            "categories": {},
            "difficulty": "Moderate9",
            "status": "Approved",
            "lastUpdated": {
                "time": "Sun Dec 17 1996 03:24:00 GMT+1000 (Australian Eastern Standard Time)",
                "person": "Fangyuan Xu"
            },
            "actions": {}
        },
        {
            "itemType": "write",
            "item": {
                "itemName": "i am item name and i am goint to tuncate",
                "itemModule": "i am module11",
                "itemStem": "i am item stem and i am going to stem",
                "itemType": "write"
            },
            "categories": {},
            "difficulty": "Moderate10",
            "status": "Approved",
            "lastUpdated": {
                "time": "Sun Dec 17 1996 03:24:00 GMT+1000 (Australian Eastern Standard Time)",
                "person": "Fangyuan Xu"
            },
            "actions": {}
        },
        {
            "itemType": "write",
            "item": {
                "itemName": "i am item name and i am goint to tuncate",
                "itemModule": "i am module12",
                "itemStem": "i am item stem and i am going to stem",
                "itemType": "write"
            },
            "categories": {},
            "difficulty": "Moderate11",
            "status": "Approved",
            "lastUpdated": {
                "time": "Sun Dec 17 1996 03:24:00 GMT+1000 (Australian Eastern Standard Time)",
                "person": "Fangyuan Xu"
            },
            "actions": {}
        },
        {
            "itemType": "write",
            "item": {
                "itemName": "i am item name and i am goint to tuncate",
                "itemModule": "i am module13",
                "itemStem": "i am item stem and i am going to stem",
                "itemType": "write"
            },
            "categories": {},
            "difficulty": "Moderate12",
            "status": "Approved",
            "lastUpdated": {
                "time": "Sun Dec 17 1996 03:24:00 GMT+1000 (Australian Eastern Standard Time)",
                "person": "Fangyuan Xu"
            },
            "actions": {}
        },
        {
            "itemType": "write",
            "item": {
                "itemName": "i am item name and i am goint to tuncate",
                "itemModule": "i am module14",
                "itemStem": "i am item stem and i am going to stem",
                "itemType": "write"
            },
            "categories": {},
            "difficulty": "Moderate13",
            "status": "Approved",
            "lastUpdated": {
                "time": "Sun Dec 17 1997 03:24:00 GMT+1000 (Australian Eastern Standard Time)",
                "person": "Fangyuan Xu"
            },
            "actions": {}
        },
        {
            "itemType": "write",
            "item": {
                "itemName": "i am item name and i am goint to tuncate",
                "itemModule": "i am module15",
                "itemStem": "i am item stem and i am going to stem",
                "itemType": "write"
            },
            "categories": {},
            "difficulty": "Moderate14",
            "status": "Approved",
            "lastUpdated": {
                "time": "Sun Dec 17 1997 03:24:00 GMT+1000 (Australian Eastern Standard Time)",
                "person": "Fangyuan Xu"
            },
            "actions": {}
        },
        {
            "itemType": "write",
            "item": {
                "itemName": "i am item name and i am goint to tuncate",
                "itemModule": "i am module16",
                "itemStem": "i am item stem and i am going to stem",
                "itemType": "write"
            },
            "categories": {},
            "difficulty": "Moderate15",
            "status": "Approved",
            "lastUpdated": {
                "time": "Sun Dec 17 1997 03:24:00 GMT+1000 (Australian Eastern Standard Time)",
                "person": "Fangyuan Xu"
            },
            "actions": {}
        },
        {
            "itemType": "write",
            "item": {
                "itemName": "i am item name and i am goint to tuncate",
                "itemModule": "i am module17",
                "itemStem": "i am item stem and i am going to stem",
                "itemType": "write"
            },
            "categories": {},
            "difficulty": "Moderate16",
            "status": "Approved",
            "lastUpdated": {
                "time": "Sun Dec 17 1997 03:24:00 GMT+1000 (Australian Eastern Standard Time)",
                "person": "Fangyuan Xu"
            },
            "actions": {}
        },
        {
            "itemType": "write",
            "item": {
                "itemName": "i am item name and i am goint to tuncate",
                "itemModule": "i am module18",
                "itemStem": "i am item stem and i am going to stem",
                "itemType": "write"
            },
            "categories": {},
            "difficulty": "Moderate17",
            "status": "Approved",
            "lastUpdated": {
                "time": "Sun Dec 17 1997 03:24:00 GMT+1000 (Australian Eastern Standard Time)",
                "person": "Fangyuan Xu"
            },
            "actions": {}
        },
        {
            "itemType": "write",
            "item": {
                "itemName": "i am item name and i am goint to tuncate",
                "itemModule": "i am module19",
                "itemStem": "i am item stem and i am going to stem",
                "itemType": "write"
            },
            "categories": {},
            "difficulty": "Moderate18",
            "status": "Approved",
            "lastUpdated": {
                "time": "Sun Dec 17 1998 03:24:00 GMT+1000 (Australian Eastern Standard Time)",
                "person": "Fangyuan Xu"
            },
            "actions": {}
        },
        {
            "itemType": "write",
            "item": {
                "itemName": "i am item name and i am goint to tuncate",
                "itemModule": "i am module20",
                "itemStem": "i am item stem and i am going to stem",
                "itemType": "write"
            },
            "categories": {},
            "difficulty": "Moderate19",
            "status": "Approved",
            "lastUpdated": {
                "time": "Sun Dec 17 1998 03:24:00 GMT+1000 (Australian Eastern Standard Time)",
                "person": "Fangyuan Xu"
            },
            "actions": {}
        },
        {
            "itemType": "write",
            "item": {
                "itemName": "i am item name and i am goint to tuncate",
                "itemModule": "i am module21",
                "itemStem": "i am item stem and i am going to stem",
                "itemType": "write"
            },
            "categories": {},
            "difficulty": "Moderate20",
            "status": "Approved",
            "lastUpdated": {
                "time": "Sun Dec 17 1998 03:24:00 GMT+1000 (Australian Eastern Standard Time)",
                "person": "Fangyuan Xu"
            },
            "actions": {}
        }
    ],
    "total": 100
}
